hayeah_pymake-0.1.2.dist-info/licenses/LICENSE
pymake/__init__.py
pymake/__main__.py
pymake/cli.py
pymake/executor.py
pymake/executor_test.py
pymake/resolver.py
pymake/resolver_test.py
pymake/sh.py
pymake/task.py
pymake/task_test.py
hayeah_pymake-0.1.2.dist-info/METADATA
hayeah_pymake-0.1.2.dist-info/WHEEL
hayeah_pymake-0.1.2.dist-info/entry_points.txt
hayeah_pymake-0.1.2.dist-info/top_level.txt
hayeah_pymake-0.1.2.dist-info/RECORD
