Metadata-Version: 2.4
Name: hayeah-pymake
Version: 0.1.2
Summary: Python Makefile alternative
Author: Howard Yeh
License-Expression: MIT
Project-URL: Homepage, https://github.com/hayeah/pymake
Project-URL: Repository, https://github.com/hayeah/pymake
Project-URL: Issues, https://github.com/hayeah/pymake/issues
Classifier: Development Status :: 3 - Alpha
Classifier: Intended Audience :: Developers
Classifier: Programming Language :: Python :: 3
Classifier: Programming Language :: Python :: 3.10
Classifier: Programming Language :: Python :: 3.11
Classifier: Programming Language :: Python :: 3.12
Requires-Python: >=3.10
License-File: LICENSE
Provides-Extra: dev
Requires-Dist: pytest; extra == "dev"
Requires-Dist: mypy; extra == "dev"
Requires-Dist: ruff; extra == "dev"
Dynamic: license-file
